glycebert/__init__.py
glycebert/classifier.py
glycebert/fusion_embedding.py
glycebert/glyph_embedding.py
glycebert/modeling_glycebert.py
glycebert/pinyin_embedding.py
glycebert/tokenization_glycebert_fast.py
glycebert-0.0.3.dist-info/LICENSE
glycebert-0.0.3.dist-info/METADATA
glycebert-0.0.3.dist-info/WHEEL
glycebert-0.0.3.dist-info/top_level.txt
glycebert-0.0.3.dist-info/RECORD
