Metadata-Version: 2.1
Name: glycebert
Version: 0.0.3
Summary: GlyceBert_pytorch
Home-page: https://github.com/JunnYu/GlyceBert_pytorch
Author: Jun Yu
Author-email: 573009727@qq.com
License: MIT
Keywords: GlyceBert,pytorch
Platform: UNKNOWN
Requires-Dist: transformers (>=4.7.0)
Requires-Dist: pypinyin
